snifa/__init__.py
snifa/_version.py
snifa/snifa.py
snifa-0.5.3.dist-info/LICENSE
snifa-0.5.3.dist-info/METADATA
snifa-0.5.3.dist-info/WHEEL
snifa-0.5.3.dist-info/top_level.txt
snifa-0.5.3.dist-info/RECORD
