Metadata-Version: 2.1
Name: snifa
Version: 0.5.3
Summary: Simple Numerical Instantaneous Frequency Approximation (SNIFA)
Home-page: https://gitlab.flavio.be/flavio/snifa
Author: Flavio Abreu Araujo
Author-email: flavio.abreuaraujo@uclouvain.be
License: MIT
Platform: UNKNOWN
Classifier: Intended Audience :: Science/Research
Classifier: Programming Language :: Python :: 3
Classifier: License :: OSI Approved :: MIT License
Classifier: Topic :: Software Development
Classifier: Topic :: Scientific/Engineering
Classifier: Operating System :: OS Independent
Requires-Python: >=3.6
Requires-Dist: numpy
Requires-Dist: scipy
